cosmol_viewer/__init__.py
cosmol_viewer/__init__.pyi
cosmol_viewer/cosmol_viewer.pypy311-pp73-x86_64-linux-gnu.so
cosmol_viewer/py.typed
cosmol_viewer-0.2.4.dist-info/METADATA
cosmol_viewer-0.2.4.dist-info/WHEEL
cosmol_viewer-0.2.4.dist-info/RECORD
