Metadata-Version: 2.4
Name: cosmol-viewer
Version: 0.2.4
Summary: Molecular visualization tools
Author-email: 95028 <wjt@cosmol.org>
Project-URL: Repository, https://github.com/COSMol-repl/COSMol-viewer
